yutilx/__init__.py
yutilx/cached_parallel_processor.py
yutilx-0.0.3.dist-info/METADATA
yutilx-0.0.3.dist-info/WHEEL
yutilx-0.0.3.dist-info/licenses/LICENSE
yutilx-0.0.3.dist-info/RECORD
