Metadata-Version: 2.4
Name: yutilx
Version: 0.0.3
Summary: Xinyu's common utilities
Project-URL: Source, https://github.com/cauyxy/yutilx/
Author-email: Xinyu Yang <cauyxy@gmail.com>
Maintainer-email: Xinyu Yang <cauyxy@gmail.com>
License-File: LICENSE
Requires-Python: >=3.9
Requires-Dist: tqdm>=4.60.0
